pydatacq/__init__.py
pydatacq/live_data.py
pydatacq/live_sds.py
pydatacq/live_window.py
pydatacq/sds.py
pydatacq/siglent.py
pydatacq-0.4.5.dist-info/METADATA
pydatacq-0.4.5.dist-info/WHEEL
pydatacq-0.4.5.dist-info/licenses/LICENSE
pydatacq-0.4.5.dist-info/RECORD
