Metadata-Version: 2.4
Name: pydatacq
Version: 0.4.5
Summary: A package for asynchronous data acquisition
Project-URL: Homepage, https://github.com/kvdijken/pydatacq
Author-email: kvdijken <sla_nippers_0x@icloud.com>
License-File: LICENSE
Classifier: License :: OSI Approved :: MIT License
Classifier: Operating System :: OS Independent
Classifier: Programming Language :: Python :: 3
Requires-Python: >=3.11
Requires-Dist: numpy
Requires-Dist: scipy
Requires-Dist: uvloop
